ultra_simple_config/__init__.py
ultra_simple_config/config.py
ultra_simple_config-0.1.0.dist-info/LICENSE
ultra_simple_config-0.1.0.dist-info/METADATA
ultra_simple_config-0.1.0.dist-info/WHEEL
ultra_simple_config-0.1.0.dist-info/RECORD
