Metadata-Version: 2.1
Name: ultra-simple-config
Version: 0.1.0
Summary: 
Author: Marc Mezger
Author-email: marc.mezger@gmail.com
Requires-Python: >=3.11,<4.0
Classifier: Programming Language :: Python :: 3
Classifier: Programming Language :: Python :: 3.11
Requires-Dist: omegaconf (>=2.3.0,<3.0.0)
